function_pattern_matching.py
function_pattern_matching-0.99a2.dist-info/DESCRIPTION.rst
function_pattern_matching-0.99a2.dist-info/METADATA
function_pattern_matching-0.99a2.dist-info/RECORD
function_pattern_matching-0.99a2.dist-info/WHEEL
function_pattern_matching-0.99a2.dist-info/metadata.json
function_pattern_matching-0.99a2.dist-info/top_level.txt
