Metadata-Version: 2.0
Name: function-pattern-matching
Version: 0.99a2
Summary: Pattern matching and guards for Python functions
Home-page: https://github.com/rasguanabana/function-pattern-matching
Author: Adrian Włosiak
Author-email: adwlosiakh@gmail.com
License: MIT
Keywords: pattern matching guards
Platform: UNKNOWN
Classifier: Development Status :: 3 - Alpha
Classifier: Intended Audience :: Developers
Classifier: License :: OSI Approved :: MIT License
Classifier: Operating System :: OS Independent
Classifier: Programming Language :: Python :: 2
Classifier: Programming Language :: Python :: 3
Classifier: Topic :: Software Development :: Libraries :: Python Modules
Requires-Dist: six
